plumbing/__init__.py
plumbing/cache.py
plumbing/color.py
plumbing/common.py
plumbing/csv_tables.py
plumbing/dataframes.py
plumbing/dependencies.py
plumbing/git.py
plumbing/graphs.py
plumbing/processes.py
plumbing/redirect.py
plumbing/runner.py
plumbing/thread.py
plumbing/timer.py
plumbing/tmpstuff.py
plumbing/databases/__init__.py
plumbing/databases/access_database.py
plumbing/databases/sqlite_database.py
plumbing/slurm/__init__.py
plumbing/slurm/existing.py
plumbing/slurm/job.py
plumbing/slurm/logged.py
plumbing/trees/__init__.py
plumbing/trees/newick.py
plumbing-2.1.9.dist-info/LICENSE.txt
plumbing-2.1.9.dist-info/METADATA
plumbing-2.1.9.dist-info/WHEEL
plumbing-2.1.9.dist-info/top_level.txt
plumbing-2.1.9.dist-info/RECORD
