Metadata-Version: 2.1
Name: plumbing
Version: 2.1.9
Summary: Helps with plumbing-type programing in python.
Home-page: http://github.com/xapple/plumbing/
Author: Lucas Sinclair
Author-email: lucas.sinclair@me.com
License: MIT
Platform: UNKNOWN
Requires-Dist: autopaths
Requires-Dist: sh
Requires-Dist: biopython
Requires-Dist: matplotlib
Requires-Dist: brewer2mpl
